jsonpointer.py
jsonpointer-1.14.data/scripts/jsonpointer
jsonpointer-1.14.dist-info/DESCRIPTION.rst
jsonpointer-1.14.dist-info/METADATA
jsonpointer-1.14.dist-info/RECORD
jsonpointer-1.14.dist-info/WHEEL
jsonpointer-1.14.dist-info/metadata.json
jsonpointer-1.14.dist-info/top_level.txt
